{
  "$schema": "http://json-schema.org/draft-07/schema#",
  "title": "Lowdefy Request Schema - GoogleSheetGetOne",
  "type": "object",
  "properties": {
    "offset": {
      "type": "number",
      "description": "The number of rows to skip from the top of the sheet.",
      "errorMessage": {
        "type": "GoogleSheetGetOne request property \"offset\" should be a number."
      }
    },
    "limit": {
      "type": "number",
      "description": "The maximum number of rows to fetch.",
      "errorMessage": {
        "type": "GoogleSheetGetOne request property \"limit\" should be a number."
      }
    },
    "filter": {
      "type": "object",
      "description": "A MongoDB query expression to filter the data.",
      "errorMessage": {
        "type": "GoogleSheetGetOne request property \"filter\" should be an object."
      }
    }
  },
  "errorMessage": {
    "type": "GoogleSheetGetOne request properties should be an object."
  }
}